PyCodeml/__init__.py
PyCodeml/classifier.py
PyCodeml/clustering.py
PyCodeml/regressor.py
PyCodeml/tunner.py
PyCodeml/utils.py
pycodeml-0.0.20.dist-info/METADATA
pycodeml-0.0.20.dist-info/WHEEL
pycodeml-0.0.20.dist-info/top_level.txt
pycodeml-0.0.20.dist-info/RECORD
