Metadata-Version: 2.4
Name: pycodeml
Version: 0.0.20
Summary: Automatically train multiple regression models and return the best one.
Home-page: https://github.com/Nachiket858/PyCodeML
Author: Nachiket Shinde
Author-email: nachiketshinde2004@gmail.com
License: MIT
Project-URL: Source, https://github.com/Nachiket858/PyCodeML
Keywords: machine learning,regression,auto-model selection,data science
Classifier: Development Status :: 4 - Beta
Classifier: Intended Audience :: Developers
Classifier: Intended Audience :: Science/Research
Classifier: License :: OSI Approved :: MIT License
Classifier: Programming Language :: Python :: 3
Classifier: Programming Language :: Python :: 3.7
Classifier: Programming Language :: Python :: 3.8
Classifier: Programming Language :: Python :: 3.9
Classifier: Programming Language :: Python :: 3.10
Classifier: Topic :: Scientific/Engineering :: Artificial Intelligence
Classifier: Topic :: Software Development :: Libraries :: Python Modules
Requires-Python: >=3.7
Requires-Dist: pandas
Requires-Dist: scikit-learn
Requires-Dist: numpy
Dynamic: author
Dynamic: author-email
Dynamic: classifier
Dynamic: description
Dynamic: description-content-type
Dynamic: home-page
Dynamic: keywords
Dynamic: license
Dynamic: project-url
Dynamic: requires-dist
Dynamic: requires-python
Dynamic: summary
